gitstats/DataCollector.py
gitstats/GitDataCollector.py
gitstats/__init__.py
gitstats/constans.py
gitstats/main.py
gitstats/py.typed
gitstats/utils.py
gitstats_forked-0.1.0.dist-info/LICENSE.txt
gitstats_forked-0.1.0.dist-info/METADATA
gitstats_forked-0.1.0.dist-info/WHEEL
gitstats_forked-0.1.0.dist-info/entry_points.txt
gitstats_forked-0.1.0.dist-info/top_level.txt
gitstats_forked-0.1.0.dist-info/RECORD
